compressed/__init__.py
compressed/bzipped.py
compressed/gzipped.py
rp_demo_reader/__init__.py
rp_demo_reader/__main__.py
rp_demo_reader/multireader.py
rp_demo_reader/compressed/__init__.py
rp_demo_reader/compressed/bzipped.py
rp_demo_reader/compressed/gzipped.py
rp_demo_reader/util/__init__.py
rp_demo_reader/util/writer.py
util/__init__.py
util/writer.py
rp_demo_reader-1.0.1.dist-info/METADATA
rp_demo_reader-1.0.1.dist-info/WHEEL
rp_demo_reader-1.0.1.dist-info/top_level.txt
rp_demo_reader-1.0.1.dist-info/RECORD
