Metadata-Version: 2.1
Name: rp-demo-reader
Version: 1.0.1
Summary: Tool fo reading various file formats
Home-page: UNKNOWN
License: UNKNOWN
Platform: UNKNOWN
